fractalize_nlp/__init__.py
fractalize_nlp/string_generators/BaseStringGenerator.py
fractalize_nlp/string_generators/CompositeStringGenerator.py
fractalize_nlp/string_generators/__init__.py
fractalize_nlp/string_generators/utils.py
test/BaseStringGenerators.py
test/__init__.py
test/resources.py
test/test_generate_order_choice_string.py
test/test_generate_sample_for_all_states.py
test/test_generate_sample_for_state.py
test/test_generate_string_for_state.py
test/test_load_sources.py
test/test_sample.py
test/test_select_state_domain_for_state.py
test/test_uniform_distribution.py
test/utils.py
fractalize_nlp-0.0.7.dist-info/LICENSE
fractalize_nlp-0.0.7.dist-info/METADATA
fractalize_nlp-0.0.7.dist-info/WHEEL
fractalize_nlp-0.0.7.dist-info/top_level.txt
fractalize_nlp-0.0.7.dist-info/RECORD
