Metadata-Version: 2.1
Name: fractalize-nlp
Version: 0.0.7
Summary: Fractalize NLP Tools
Home-page: https://github.com/fractal-dataminds/fractalize_nlp
Author: Fractal Dataminds
Author-email: gireesh@fractal-data.com
License: UNKNOWN
Platform: UNKNOWN
Classifier: Programming Language :: Python :: 3
Classifier: License :: OSI Approved :: MIT License
Classifier: Operating System :: OS Independent
Requires-Python: >=3.6
